MANIFEST.in
README.md
VERSION
pyproject.toml
setup.cfg
setup.py
jsonmarshal/__init__.py
jsonmarshal/exceptions.py
jsonmarshal/fields.py
jsonmarshal/marshal.py
jsonmarshal/types.py
jsonmarshal/unmarshal.py
jsonmarshal.egg-info/PKG-INFO
jsonmarshal.egg-info/SOURCES.txt
jsonmarshal.egg-info/dependency_links.txt
jsonmarshal.egg-info/not-zip-safe
jsonmarshal.egg-info/requires.txt
jsonmarshal.egg-info/top_level.txt
jsonmarshal/utils/__init__.py
jsonmarshal/utils/typing.py
jsonmarshal/utils/warnings.py