Metadata-Version: 2.1
Name: jsonmarshal
Version: 0.0.1rc7
Summary: Marshal JSON to/from python dataclasses.
Home-page: https://github.com/MikeWooster/jsonmarshal
Author: Mike Wooster
Author-email: 
License: UNKNOWN
Platform: UNKNOWN
Classifier: Development Status :: 1 - Planning
Classifier: Programming Language :: Python :: 3.7
Classifier: License :: OSI Approved :: MIT License
Classifier: Operating System :: OS Independent
Classifier: Intended Audience :: Developers
Requires-Python: >=3.6
Provides-Extra: docs
Provides-Extra: deploy
Provides-Extra: test
Provides-Extra: dev
Provides-Extra: lint
